{
  "persons": [
    {
      "name": "Arto Hellas",
      "number": "24895728475",
      "id": 1
    },
    {
      "name": "Ada Lovelace",
      "number": "39-44-5323523",
      "id": 2
    },
    {
      "name": "Dan Abramov",
      "number": "12-43-234345",
      "id": 3
    },
    {
      "name": "Mary Poppendieck",
      "number": "39-23-6423122",
      "id": 4
    },
    {
      "name": "bobaba",
      "number": "2384789123",
      "id": 5
    },
    {
      "name": "hitle",
      "number": "1471038",
      "id": 6
    }
  ]
}